pyramid_sqlalchemy_utility
