Metadata-Version: 1.0
Name: pyramid-sqlalchemy-utility
Version: 0.1
Summary: Pyramid sqlalchemy extension
Home-page: UNKNOWN
Author: Hadrien David
Author-email: hadrien@ectobal.com
License: UNKNOWN
Platform: UNKNOWN
